deephaven_mcp/__init__.py
deephaven_mcp/_exceptions.py
deephaven_mcp/_logging.py
deephaven_mcp/_monkeypatch.py
deephaven_mcp/_version.py
deephaven_mcp/io.py
deephaven_mcp/openai.py
deephaven_mcp/queries.py
deephaven_mcp/client/__init__.py
deephaven_mcp/client/_auth_client.py
deephaven_mcp/client/_base.py
deephaven_mcp/client/_controller_client.py
deephaven_mcp/client/_protobuf.py
deephaven_mcp/client/_session.py
deephaven_mcp/client/_session_factory.py
deephaven_mcp/config/__init__.py
deephaven_mcp/config/_community_session.py
deephaven_mcp/config/_enterprise_system.py
deephaven_mcp/formatters/__init__.py
deephaven_mcp/formatters/_csv.py
deephaven_mcp/formatters/_json.py
deephaven_mcp/formatters/_markdown.py
deephaven_mcp/formatters/_xml.py
deephaven_mcp/formatters/_yaml.py
deephaven_mcp/mcp_docs_server/__init__.py
deephaven_mcp/mcp_docs_server/_mcp.py
deephaven_mcp/mcp_docs_server/main.py
deephaven_mcp/mcp_systems_server/__init__.py
deephaven_mcp/mcp_systems_server/_mcp.py
deephaven_mcp/mcp_systems_server/main.py
deephaven_mcp/resource_manager/__init__.py
deephaven_mcp/resource_manager/_manager.py
deephaven_mcp/resource_manager/_registry.py
deephaven_mcp/resource_manager/_registry_combined.py
deephaven_mcp-0.0.13.dist-info/licenses/LICENSE
deephaven_mcp-0.0.13.dist-info/METADATA
deephaven_mcp-0.0.13.dist-info/WHEEL
deephaven_mcp-0.0.13.dist-info/entry_points.txt
deephaven_mcp-0.0.13.dist-info/top_level.txt
deephaven_mcp-0.0.13.dist-info/RECORD
