Metadata-Version: 2.4
Name: deephaven-mcp
Version: 0.0.13
Summary: Unified Python package providing Model Context Protocol (MCP) servers for Deephaven: orchestrate Community Core data workers and power Documentation Q&A with LLMs. Supports AI-driven data workflows and agentic documentation assistance in a single deployable package.
Author-email: Deephaven Data Labs <support@deephaven.io>
License: Apache-2.0
Project-URL: Homepage, https://deephaven.io
Project-URL: Documentation, https://deephaven.io/docs/
Project-URL: Repository, https://github.com/deephaven/deephaven-mcp
Project-URL: Issues, https://github.com/deephaven/deephaven-mcp/issues
Keywords: deephaven,mcp,model-context-protocol,ai,documentation,llm,orchestration,community-core,docs,q&a
Classifier: Development Status :: 4 - Beta
Classifier: Intended Audience :: Developers
Classifier: License :: OSI Approved :: Apache Software License
Classifier: Programming Language :: Python :: 3
Classifier: Programming Language :: Python :: 3.11
Classifier: Programming Language :: Python :: 3.12
Classifier: Programming Language :: Python :: 3.13
Classifier: Topic :: Scientific/Engineering :: Artificial Intelligence
Classifier: Topic :: Software Development :: Libraries :: Python Modules
Classifier: Topic :: System :: Distributed Computing
Requires-Python: >=3.11
License-File: LICENSE
Requires-Dist: typing_extensions>=4.3.0
Requires-Dist: aiofiles>=23.2.1
Requires-Dist: aiohttp>=3.11.18
Requires-Dist: autogen-ext[mcp]>=0.5.4
Requires-Dist: mcp[cli]>=1.12.0
Requires-Dist: mcp-proxy
Requires-Dist: pydeephaven>=0.39
Requires-Dist: fastapi>=0.116.0
Requires-Dist: uvicorn[standard]>=0.35.0
Requires-Dist: openai>=1.0.0
Requires-Dist: pydantic>=2.0.0
Requires-Dist: python-dotenv>=1.0.0
Requires-Dist: aiolimiter>=1.1.0
Requires-Dist: autogen-core
Requires-Dist: autogen-ext
Requires-Dist: google-cloud-logging>=3.8.0
Requires-Dist: psutil>=5.9.0
Requires-Dist: pyyaml>=6.0
Provides-Extra: test
Requires-Dist: pytest>=8.0.0; extra == "test"
Requires-Dist: pytest-asyncio>=0.23.0; extra == "test"
Requires-Dist: pytest-cov>=4.1.0; extra == "test"
Provides-Extra: dev
Requires-Dist: black>=24.0.0; extra == "dev"
Requires-Dist: ruff>=0.1.0; extra == "dev"
Requires-Dist: isort>=5.12.0; extra == "dev"
Requires-Dist: pydocstyle>=6.3.0; extra == "dev"
Requires-Dist: mypy>=1.6.0; extra == "dev"
Requires-Dist: types-aiofiles; extra == "dev"
Requires-Dist: pre-commit>=3.4.0; extra == "dev"
Requires-Dist: deephaven-server>=0.39; extra == "dev"
Requires-Dist: pytest>=8.0.0; extra == "dev"
Requires-Dist: pytest-asyncio>=0.23.0; extra == "dev"
Requires-Dist: pytest-cov>=4.1.0; extra == "dev"
Requires-Dist: httpx[cli]>=0.24.0; extra == "dev"
Requires-Dist: typing_extensions>=4.3.0; extra == "dev"
Provides-Extra: coreplus
Dynamic: license-file
